hello_world.py
hello_world_nagarjun-0.2.1.dist-info/METADATA
hello_world_nagarjun-0.2.1.dist-info/WHEEL
hello_world_nagarjun-0.2.1.dist-info/top_level.txt
hello_world_nagarjun-0.2.1.dist-info/RECORD
