Metadata-Version: 2.1
Name: hello-world-nagarjun
Version: 0.2.1
Summary: A sample Python project
Home-page: UNKNOWN
Author: Nagarjun
License: MIT
Platform: UNKNOWN
Requires-Python: >=3.6.0
Requires-Dist: numpy
